.gitattributes
MANIFEST.in
NEWS.rst
README.rst
requirements.txt
setup.cfg
setup.py
versioneer.py
airr/__init__.py
airr/_version.py
airr/interface.py
airr/io.py
airr/schema.py
airr/tools.py
airr.egg-info/PKG-INFO
airr.egg-info/SOURCES.txt
airr.egg-info/dependency_links.txt
airr.egg-info/entry_points.txt
airr.egg-info/not-zip-safe
airr.egg-info/requires.txt
airr.egg-info/top_level.txt
airr/specs/__init__.py
airr/specs/airr-schema.yaml
tests/__init__.py
tests/test_interface.py
tests/test_io.py
tests/data/bad_genotype_set.json
tests/data/bad_germline_set.json
tests/data/bad_rearrangement.tsv
tests/data/bad_repertoire.yaml
tests/data/extra_rearrangement.tsv
tests/data/good_combined_airr.json
tests/data/good_combined_airr.yaml
tests/data/good_genotype_set.json
tests/data/good_germline_set.json
tests/data/good_rearrangement.tsv
tests/data/good_repertoire.yaml