Metadata-Version: 2.1
Name: airr
Version: 1.5.1
Summary: AIRR Community Data Representation Standard reference library for antibody and TCR sequencing data.
Home-page: http://docs.airr-community.org
Author: AIRR Community
Author-email: 
License: CC BY 4.0
Keywords: AIRR,bioinformatics,sequencing,immunoglobulin,antibody,adaptive immunity,T cell,B cell,BCR,TCR
Classifier: Intended Audience :: Science/Research
Classifier: Natural Language :: English
Classifier: Operating System :: OS Independent
Classifier: Programming Language :: Python :: 3
Classifier: Topic :: Scientific/Engineering :: Bio-Informatics
